{
    "id": "536991b0a3a729239d203d13",
    "recommendations": [
        {
            "id": "5369995ba3a729239d205221",
            "score": 26
        },
        {
            "id": "536995f5a3a729239d20487f",
            "score": 23
        },
        {
            "id": "55717121c751df588de5726c",
            "score": 21
        },
        {
            "id": "545b55e1c751df52de9b6045",
            "score": 19
        },
        {
            "id": "59b0020ec751df07d5f13bcf",
            "score": 19
        },
        {
            "id": "decoupage-des-departements-metropolitains-issu-d-openstreetmap",
            "score": 19
        }
    ]
}